azureml/__init__.py
azureml/monitoring/__init__.py
azureml/monitoring/modeldatacollector.py
azureml/monitoring/_logging/__init__.py
azureml/monitoring/_logging/constants.py
azureml/monitoring/_logging/telemetry_logger.py
azureml/monitoring/_logging/telemetry_logger_context_filter.py
azureml/monitoring/_logging/telemetry_logger_context_formatter.py
azureml/monitoring/tools/modeldatacollector/lib/native/Windows/appinsights_shared.dll
azureml/monitoring/tools/modeldatacollector/lib/native/Windows/boost_atomic-vc140-mt-1_64.dll
azureml/monitoring/tools/modeldatacollector/lib/native/Windows/boost_chrono-vc140-mt-1_64.dll
azureml/monitoring/tools/modeldatacollector/lib/native/Windows/boost_container-vc140-mt-1_64.dll
azureml/monitoring/tools/modeldatacollector/lib/native/Windows/boost_context-vc140-mt-1_64.dll
azureml/monitoring/tools/modeldatacollector/lib/native/Windows/boost_coroutine-vc140-mt-1_64.dll
azureml/monitoring/tools/modeldatacollector/lib/native/Windows/boost_date_time-vc140-mt-1_64.dll
azureml/monitoring/tools/modeldatacollector/lib/native/Windows/boost_fiber-vc140-mt-1_64.dll
azureml/monitoring/tools/modeldatacollector/lib/native/Windows/boost_filesystem-vc140-mt-1_64.dll
azureml/monitoring/tools/modeldatacollector/lib/native/Windows/boost_graph-vc140-mt-1_64.dll
azureml/monitoring/tools/modeldatacollector/lib/native/Windows/boost_iostreams-vc140-mt-1_64.dll
azureml/monitoring/tools/modeldatacollector/lib/native/Windows/boost_locale-vc140-mt-1_64.dll
azureml/monitoring/tools/modeldatacollector/lib/native/Windows/boost_log-vc140-mt-1_64.dll
azureml/monitoring/tools/modeldatacollector/lib/native/Windows/boost_log_setup-vc140-mt-1_64.dll
azureml/monitoring/tools/modeldatacollector/lib/native/Windows/boost_math_c99-vc140-mt-1_64.dll
azureml/monitoring/tools/modeldatacollector/lib/native/Windows/boost_math_c99f-vc140-mt-1_64.dll
azureml/monitoring/tools/modeldatacollector/lib/native/Windows/boost_math_c99l-vc140-mt-1_64.dll
azureml_monitoring-0.1.0a21.dist-info/METADATA
azureml_monitoring-0.1.0a21.dist-info/WHEEL
azureml_monitoring-0.1.0a21.dist-info/top_level.txt
azureml_monitoring-0.1.0a21.dist-info/RECORD
