Metadata-Version: 2.1
Name: azureml-monitoring
Version: 0.1.0a21
Summary: Microsoft Azure Machine Learning Python SDK for collecting model data during operationalization
Home-page: UNKNOWN
Author: Microsoft Corporation
Author-email: amlmodeltracking@microsoft.com
License: MIT
Requires-Dist: azureml-telemetry
